emso_metadata_harmonizer/__init__.py
emso_metadata_harmonizer/dataset_generator.py
emso_metadata_harmonizer/erddap_configurator.py
emso_metadata_harmonizer/report.py
emso_metadata_harmonizer/erddap/__init__.py
emso_metadata_harmonizer/erddap/datasets_xml.py
emso_metadata_harmonizer/erddap/erddap.py
emso_metadata_harmonizer/metadata/__init__.py
emso_metadata_harmonizer/metadata/autofill.py
emso_metadata_harmonizer/metadata/constants.py
emso_metadata_harmonizer/metadata/dataset.py
emso_metadata_harmonizer/metadata/emso.py
emso_metadata_harmonizer/metadata/merge.py
emso_metadata_harmonizer/metadata/metadata_templates.py
emso_metadata_harmonizer/metadata/minmeta.py
emso_metadata_harmonizer/metadata/netcdf.py
emso_metadata_harmonizer/metadata/tests.py
emso_metadata_harmonizer/metadata/utils.py
emso_metadata_harmonizer/metadata/waterframe.py
emso_metadata_harmonizer/metadata/xmlutils.py
emso_metadata_harmonizer-0.4.8.dist-info/METADATA
emso_metadata_harmonizer-0.4.8.dist-info/WHEEL
emso_metadata_harmonizer-0.4.8.dist-info/top_level.txt
emso_metadata_harmonizer-0.4.8.dist-info/RECORD
