Metadata-Version: 2.1
Name: emso-metadata-harmonizer
Version: 0.4.8
Summary: Toolbox for creating/assessing EMSO-compliant NetCDF datasets and integrate them into ERDDAP services
Author-email: Enoc Martínez <enoc.martinez@upc.edu>
Maintainer-email: Enoc Martínez <enoc.martinez@upc.edu>
Project-URL: Homepage, https://github.com/EnocMartinez/stadb
Project-URL: Source, https://github.com/EnocMartinez/stadb
Keywords: emso,metadata,setuptools,development,erddap
Classifier: Development Status :: 4 - Beta
Classifier: Intended Audience :: Developers
Classifier: Topic :: Software Development :: Build Tools
Classifier: License :: OSI Approved :: MIT License
Classifier: Programming Language :: Python :: 3
Classifier: Programming Language :: Python :: 3.8
Classifier: Programming Language :: Python :: 3.9
Classifier: Programming Language :: Python :: 3.10
Classifier: Programming Language :: Python :: 3.11
Classifier: Programming Language :: Python :: 3.12
Classifier: Programming Language :: Python :: 3 :: Only
Requires-Python: >=3.8
Requires-Dist: certifi >=2022.12.7
Requires-Dist: charset-normalizer >=3.1.0
Requires-Dist: idna >=3.4
Requires-Dist: markdown-it-py >=2.2.0
Requires-Dist: mdurl >=0.1.2
Requires-Dist: numpy >=1.24.2
Requires-Dist: pandas >=1.5.3
Requires-Dist: Pygments >=2.14.0
Requires-Dist: python-dateutil >=2.8.2
Requires-Dist: pytz >=2022.7.1
Requires-Dist: requests >=2.28.2
Requires-Dist: rich >=13.3.2
Requires-Dist: six >=1.16.0
Requires-Dist: typing-extensions >=4.5.0
Requires-Dist: urllib3 >=1.26.14
Requires-Dist: openpyxl >=3.1.2
Requires-Dist: netCDF4 ~=1.6.3
Requires-Dist: matplotlib ~=3.7.1
